pyworkbook/__init__.py
pyworkbook/exec.py
pyworkbook/flask_call.py
pyworkbook/iframe.py
pyworkbook/quiz.py
pyworkbook/test.py
pyworkbook/vorlagen.py
pyworkbook-0.0.8.dist-info/LICENSE.txt
pyworkbook-0.0.8.dist-info/METADATA
pyworkbook-0.0.8.dist-info/WHEEL
pyworkbook-0.0.8.dist-info/top_level.txt
pyworkbook-0.0.8.dist-info/RECORD
