Metadata-Version: 2.1
Name: pyworkbook
Version: 0.0.8
Summary: Erweiterung für Jupyter Notebooks für den Informatik Unterricht
Home-page: UNKNOWN
Author: Stefan Hickl
Author-email: <kontakt@stefanhickl.de>
License: MIT
Keywords: python,jupyter,school
Platform: UNKNOWN
Classifier: Programming Language :: Python :: 3
Classifier: Intended Audience :: Education
Classifier: Operating System :: Unix
Classifier: Operating System :: MacOS :: MacOS X
Classifier: Operating System :: Microsoft :: Windows
Requires-Dist: Flask (>=2.3.2)
Requires-Dist: ipython (>=8.9.0)
Requires-Dist: ipywidgets (>=8.1.0)
Provides-Extra: dev
Requires-Dist: twine (>=4.0.2) ; extra == 'dev'
